{
  "category": "spor_ayakkabi",
  "products": [
    {
      "product_id": "b2b6e429a5e4",
      "product_name": "BENİMOLSUN Unısex Beyaz Sneaker - Fiyatı, Yorumları",
      "product_url": "https://www.trendyol.com/benimolsun/unisex-beyaz-sneaker-p-846165465",
      "total_reviews": 50,
      "overall_score": 4.88,
      "overall_sentiment": "positive",
      "aspect_count": 6
    },
    {
      "product_id": "06b6ec8804b9",
      "product_name": "pasyone Mavi - Kadın Spor Ayakkabı - Fiyatı, Yorumları",
      "product_url": "https://www.trendyol.com/pasyone/mavi-kadin-spor-ayakkabi-p-141994765",
      "total_reviews": 50,
      "overall_score": 4.68,
      "overall_sentiment": "positive",
      "aspect_count": 6
    },
    {
      "product_id": "fe9d4b9deccd",
      "product_name": "Tonny Black Unisex Beyaz Siyah Termo Taban Yanı Şeritli Bağcıklı Spor Ayakkabı -",
      "product_url": "https://www.trendyol.com/tonny-black/unisex-beyaz-siyah-termo-taban-yani-seritli-bagcikli-spor-ayakkabi-p-879885114",
      "total_reviews": 50,
      "overall_score": 4.74,
      "overall_sentiment": "positive",
      "aspect_count": 8
    },
    {
      "product_id": "a8c8e868b437",
      "product_name": "Tonny Black Unisex Beyaz Nefes Alabilen Kumaş Poli Taban Bağcıklı Spor Ayakkabı ",
      "product_url": "https://www.trendyol.com/tonny-black/unisex-beyaz-nefes-alabilen-kumas-poli-taban-bagcikli-spor-ayakkabi-p-822478962",
      "total_reviews": 50,
      "overall_score": 5.0,
      "overall_sentiment": "positive",
      "aspect_count": 8
    },
    {
      "product_id": "6322c58e9e2d",
      "product_name": "SOLAZER Kadın Beyaz Günlük Sneaker - Fiyatı, Yorumları",
      "product_url": "https://www.trendyol.com/solazer/kadin-beyaz-gunluk-sneaker-p-962705088",
      "total_reviews": 50,
      "overall_score": 4.66,
      "overall_sentiment": "positive",
      "aspect_count": 6
    },
    {
      "product_id": "95370d1df8c2",
      "product_name": "SOHO Beyaz-Pudra-Mavi Kadın Sneaker 18147 - Fiyatı, Yorumları",
      "product_url": "https://www.trendyol.com/soho/beyaz-pudra-mavi-kadin-sneaker-18147-p-747695323",
      "total_reviews": 50,
      "overall_score": 4.94,
      "overall_sentiment": "positive",
      "aspect_count": 6
    },
    {
      "product_id": "c4ac408202c5",
      "product_name": "SEOUL SPORT SHOES Cherry Love Air – Kiraz Nakışlı Beyaz Kadın Sneaker Spor Ayakk",
      "product_url": "https://www.trendyol.com/seoul-sport-shoes/cherry-love-air-kiraz-nakisli-beyaz-kadin-sneaker-spor-ayakkabi-p-1016890694",
      "total_reviews": 50,
      "overall_score": 4.74,
      "overall_sentiment": "positive",
      "aspect_count": 8
    },
    {
      "product_id": "024257edb303",
      "product_name": "Riccon Beyaz Beyaz Kadın Sneaker 0012255 - Fiyatı, Yorumları",
      "product_url": "https://www.trendyol.com/riccon/beyaz-beyaz-kadin-sneaker-0012255-p-241528489",
      "total_reviews": 50,
      "overall_score": 4.88,
      "overall_sentiment": "positive",
      "aspect_count": 8
    },
    {
      "product_id": "03b3e167b50e",
      "product_name": "Pull and Bear Spor Ayakkabı Koşu Ayakkabısı Fiyatı, Yorumları",
      "product_url": "https://www.trendyol.com/pull-bear/kosu-tipi-spor-ayakkabi-p-333548407",
      "total_reviews": 50,
      "overall_score": 4.86,
      "overall_sentiment": "positive",
      "aspect_count": 6
    },
    {
      "product_id": "8c30f9b90d7f",
      "product_name": "pasyone Siyah - Unisex Yazlık Sneaker Ayakkabı - Fiyatı, Yorumları",
      "product_url": "https://www.trendyol.com/pasyone/siyah-unisex-yazlik-sneaker-ayakkabi-p-242585669",
      "total_reviews": 50,
      "overall_score": 5.0,
      "overall_sentiment": "positive",
      "aspect_count": 6
    },
    {
      "product_id": "1decfab0fbb3",
      "product_name": "pasyone Siyah Kadın Sneaker Günlük Ayakkabı - Fiyatı, Yorumları",
      "product_url": "https://www.trendyol.com/pasyone/siyah-kadin-sneaker-gunluk-ayakkabi-p-847264596",
      "total_reviews": 50,
      "overall_score": 4.82,
      "overall_sentiment": "positive",
      "aspect_count": 7
    },
    {
      "product_id": "e68bd6e00672",
      "product_name": "pasyone Siyah - Kadın Fileli Sneaker Günlük Ayakkabı - Fiyatı, Yorumları",
      "product_url": "https://www.trendyol.com/pasyone/siyah-kadin-fileli-sneaker-gunluk-ayakkabi-p-235310350",
      "total_reviews": 50,
      "overall_score": 4.9,
      "overall_sentiment": "positive",
      "aspect_count": 6
    },
    {
      "product_id": "42ebb85019d4",
      "product_name": "Dark Seer Beyaz Unisex Sneaker - Fiyatı, Yorumları",
      "product_url": "https://www.trendyol.com/dark-seer/beyaz-unisex-sneaker-p-42713792",
      "total_reviews": 50,
      "overall_score": 4.94,
      "overall_sentiment": "positive",
      "aspect_count": 6
    },
    {
      "product_id": "3d01a1c0f77f",
      "product_name": "pasyone Siyah Kadın Fileli Günlük Ayakkabı - Fiyatı, Yorumları",
      "product_url": "https://www.trendyol.com/pasyone/siyah-kadin-fileli-gunluk-ayakkabi-p-861184481",
      "total_reviews": 50,
      "overall_score": 4.7,
      "overall_sentiment": "positive",
      "aspect_count": 8
    },
    {
      "product_id": "cb17a970a839",
      "product_name": "pasyone Lacivert Kadın Sneaker Günlük Ayakkabı - Fiyatı, Yorumları",
      "product_url": "https://www.trendyol.com/pasyone/lacivert-kadin-sneaker-gunluk-ayakkabi-p-891728961",
      "total_reviews": 50,
      "overall_score": 4.72,
      "overall_sentiment": "positive",
      "aspect_count": 8
    },
    {
      "product_id": "1bc0070a3ceb",
      "product_name": "pasyone Krep Kadın Günlük Şık Sneaker Spor Ayakkabı - Fiyatı, Yorumları",
      "product_url": "https://www.trendyol.com/pasyone/krep-kadin-gunluk-sik-sneaker-spor-ayakkabi-p-980983116",
      "total_reviews": 50,
      "overall_score": 4.9,
      "overall_sentiment": "positive",
      "aspect_count": 7
    },
    {
      "product_id": "2817958c099d",
      "product_name": "pasyone Gri Kadın Sneaker Günlük Ayakkabı - Fiyatı, Yorumları",
      "product_url": "https://www.trendyol.com/pasyone/gri-kadin-sneaker-gunluk-ayakkabi-p-847264498",
      "total_reviews": 50,
      "overall_score": 4.78,
      "overall_sentiment": "positive",
      "aspect_count": 6
    },
    {
      "product_id": "1172b0ca841a",
      "product_name": "pasyone Beyaz Kadın Sneaker Günlük Ayakkabı - Fiyatı, Yorumları",
      "product_url": "https://www.trendyol.com/pasyone/beyaz-kadin-sneaker-gunluk-ayakkabi-p-1070766714",
      "total_reviews": 50,
      "overall_score": 4.62,
      "overall_sentiment": "positive",
      "aspect_count": 8
    },
    {
      "product_id": "cd1dd6a71a91",
      "product_name": "pasyone Beyaz - Kadın Fileli Sneaker Günlük Ayakkabı - Fiyatı, Yorumları",
      "product_url": "https://www.trendyol.com/pasyone/beyaz-kadin-fileli-sneaker-gunluk-ayakkabi-p-235310779",
      "total_reviews": 50,
      "overall_score": 4.84,
      "overall_sentiment": "positive",
      "aspect_count": 5
    },
    {
      "product_id": "c26a44646bda",
      "product_name": "N MODA Unisex Beyaz Siyah Termo Taban Yanı Şeritli Bağcıklı Spor Ayakkabı Sneake",
      "product_url": "https://www.trendyol.com/n-moda/unisex-beyaz-siyah-termo-taban-yani-seritli-bagcikli-spor-ayakkabi-sneaker-p-1064048589",
      "total_reviews": 50,
      "overall_score": 4.32,
      "overall_sentiment": "neutral",
      "aspect_count": 6
    },
    {
      "product_id": "5cb04822def8",
      "product_name": "Moda Değirmeni Bej - Kadın Air Sneaker Md1147-101-0001 - Fiyatı, Yorumları",
      "product_url": "https://www.trendyol.com/moda-degirmeni/bej-kadin-air-sneaker-md1147-101-0001-p-379050015",
      "total_reviews": 50,
      "overall_score": 4.56,
      "overall_sentiment": "positive",
      "aspect_count": 7
    },
    {
      "product_id": "39e551ada368",
      "product_name": "McDark Yüksek Taban Beyaz Siyah Günlük Sneakers Ayakkabı - Fiyatı, Yorumları",
      "product_url": "https://www.trendyol.com/mcdark/yuksek-taban-beyaz-siyah-gunluk-sneakers-ayakkabi-p-810561180",
      "total_reviews": 50,
      "overall_score": 4.8,
      "overall_sentiment": "positive",
      "aspect_count": 7
    },
    {
      "product_id": "74ce14381109",
      "product_name": "infinite8 Unisex Triko Sneaker Spor Ayakkabı – Hafif Taban, Günlük & Yürüyüş Mod",
      "product_url": "https://www.trendyol.com/infinite8/unisex-triko-sneaker-spor-ayakkabi-hafif-taban-gunluk-yuruyus-modeli-sk01-p-807062121",
      "total_reviews": 50,
      "overall_score": 4.96,
      "overall_sentiment": "positive",
      "aspect_count": 5
    },
    {
      "product_id": "1d19e72a4e3e",
      "product_name": "galya shoes Unisex Spor Ayakkabı Rahat Ve Konforlu Ayakkabısı - Fiyatı, Yorumlar",
      "product_url": "https://www.trendyol.com/galya-shoes/unisex-spor-ayakkabi-rahat-ve-konforlu-ayakkabisi-p-904033531",
      "total_reviews": 50,
      "overall_score": 4.74,
      "overall_sentiment": "positive",
      "aspect_count": 6
    },
    {
      "product_id": "e552bab05595",
      "product_name": "Dark Seer Sneaker Kadın Beyaz Pudra Yorumları ve Fiyatı",
      "product_url": "https://www.trendyol.com/dark-seer/kadin-beyaz-pudra-sneaker-p-68329560",
      "total_reviews": 50,
      "overall_score": 4.96,
      "overall_sentiment": "positive",
      "aspect_count": 7
    },
    {
      "product_id": "666a892ca84a",
      "product_name": "XStep Xtep Spor Ayak - Fiyatı, Yorumları",
      "product_url": "https://www.trendyol.com/xstep/xtep-spor-ayak-p-251814605",
      "total_reviews": 50,
      "overall_score": 5.0,
      "overall_sentiment": "positive",
      "aspect_count": 8
    },
    {
      "product_id": "8ac4a4f73c96",
      "product_name": "Stradivarius Beyaz Spor Ayakkabı - Fiyatı, Yorumları",
      "product_url": "https://www.trendyol.com/stradivarius/beyaz-spor-ayakkabi-p-37733434",
      "total_reviews": 48,
      "overall_score": 4.71,
      "overall_sentiment": "positive",
      "aspect_count": 7
    },
    {
      "product_id": "485ce9d09095",
      "product_name": "U.S. Polo Assn. MAYBE WMN 5PR Beyaz Kadın Sneaker - Fiyatı, Yorumları",
      "product_url": "https://www.trendyol.com/u-s-polo-assn/maybe-wmn-5pr-beyaz-kadin-sneaker-p-978177648",
      "total_reviews": 40,
      "overall_score": 4.95,
      "overall_sentiment": "positive",
      "aspect_count": 6
    },
    {
      "product_id": "9429720f78a4",
      "product_name": "Liger Unisex Bağcıklı Spor Sneaker Ayakkabı BEYAZ - BEYAZ - Fiyatı, Yorumları",
      "product_url": "https://www.trendyol.com/liger/unisex-bagcikli-spor-sneaker-ayakkabi-beyaz-beyaz-p-905059922",
      "total_reviews": 19,
      "overall_score": 3.58,
      "overall_sentiment": "neutral",
      "aspect_count": 5
    },
    {
      "product_id": "d077a7df835a",
      "product_name": "U.S. Polo Assn. REXHA 5PR Bej Kadın Sneaker - Fiyatı, Yorumları",
      "product_url": "https://www.trendyol.com/u-s-polo-assn/rexha-5pr-bej-kadin-sneaker-p-1043305047",
      "total_reviews": 18,
      "overall_score": 4.83,
      "overall_sentiment": "positive",
      "aspect_count": 3
    }
  ]
}