{
  "product_id": "0eee6b8729c8",
  "product_name": "BiavSi Toparlayıcı Etkili Yüksek Bel Kadın Günlük Ve Spor Tayt - Fiyatı, Yorumları",
  "product_url": "https://www.trendyol.com/biavsi/toparlayici-etkili-yuksek-bel-kadin-gunluk-ve-spor-tayt-p-121735459",
  "category": "kadin_tayt",
  "category_label": "Kadın Tayt",
  "total_reviews": 50,
  "overall_score": 4.92,
  "overall_sentiment": "positive",
  "stars": "★★★★½",
  "summary": "**BiavSi Toparlayıcı Etkili Yüksek Bel Kadın Günlük Ve Sp** için 50 müşteri yorumu incelenmiştir. Ürün, kullanıcılar tarafından son derece olumlu karşılanmakta ve yüksek puan almaktadır.\n• **Rahat** konusunda kullanıcıların büyük bölümü olumlu deneyimini paylaşmaktadır; **olmasına** ve **rağmen** konusu özellikle vurgulanmaktadır. Örnek kullanıcı ifadesi: \"68 boy m aldım tam oldu kalçam geniş olmasına rağmen tam sardı yüksek bel oluşu da ço…\"\n• **Duruşu & Kalitesi**, müşteriler tarafından özellikle takdir gören bir özellik olarak öne çıkmaktadır, **göründüğü** ve **sardı** başta olmak üzere. Örnek kullanıcı ifadesi: \"Beklediğimden de güzel geldi içiniz rahat kendi bedeninizi alabilirsiniz\"\n• Kullanıcılar **Kaliteli Rahat** hakkında genel itibarıyla memnuniyetlerini dile getirmektedir; **toparlayıcı** ve **bedeni** konusu özellikle vurgulanmaktadır. Örnek kullanıcı ifadesi: \"Ayyy harika bi ürün çok beğendim çok güzel tam göründüğü gibi s beden aldım tam oldu…\"\n• **Kumaşı & Farklı Renkleri** açısından değerlendirmeler son derece olumlu bir tablo ortaya koymaktadır, **bedeni** ve **rengi** başta olmak üzere. Örnek kullanıcı ifadesi: \"Kumaşı aşırı güzel yumuşacık asla iç belli etmiyor beli falan da çok rahat çok teşekk…\"\n• Müşteri yorumlarında **Fiyat Performans** başlığı altında yoğun bir memnuniyet gözlemlenmektedir; **fiyata** ve **efsane** konusu özellikle vurgulanmaktadır. Örnek kullanıcı ifadesi: \"Beklediğimden güzel cıktı tam beden alabilirsiniz güzel topluyor fiyat olarak da cok…\"",
  "score_distribution": {
    "1": 0,
    "2": 0,
    "3": 0,
    "4": 4,
    "5": 46
  },
  "aspects": [
    {
      "name": "Rahat",
      "review_count": 13,
      "avg_score": 4.85,
      "sentiment": "positive",
      "sentiment_label": "Olumlu",
      "top_terms": [
        "kilo",
        "kilo rahat",
        "asla",
        "olmasına",
        "rağmen",
        "fiyat performans",
        "performans",
        "rahat rahat"
      ],
      "positive_pct": 84.6,
      "negative_pct": 0.0,
      "neutral_pct": 15.4,
      "sample_reviews": [
        "tayt çok güzel 75 kg 1.68 boy m aldım tam oldu kalçam geniş olmasına rağmen tam sardı yüksek bel oluşu da çok güzel",
        "bayıldım bu diyata bu kalite inanılmaz kesinlikle alın aldırın 65 kiloyum 155 boyum tam beden l",
        "aşırı beğendim vücudunu sarıyor ve büyük almanıza gerek yok 56 kiloyum s aldım"
      ],
      "all_reviews": [
        {
          "text": "tayt çok güzel 75 kg 1.68 boy m aldım tam oldu kalçam geniş olmasına rağmen tam sardı yüksek bel oluşu da çok güzel",
          "score": 5.0
        },
        {
          "text": "173 boy 57 kilo m beden süper oldu kurtarıcı bir parça",
          "score": 5.0
        },
        {
          "text": "69 kiloya l beden güzel toparladı ayrıca kumaşıda çok güzel ve kaliteli",
          "score": 5.0
        },
        {
          "text": "bayıldım bu diyata bu kalite inanılmaz kesinlikle alın aldırın 65 kiloyum 155 boyum tam beden l",
          "score": 5.0
        },
        {
          "text": "aşırı beğendim vücudunu sarıyor ve büyük almanıza gerek yok 56 kiloyum s aldım",
          "score": 4.0
        }
      ],
      "icon": "💬"
    },
    {
      "name": "Duruşu & Kalitesi",
      "review_count": 12,
      "avg_score": 4.83,
      "sentiment": "positive",
      "sentiment_label": "Olumlu",
      "top_terms": [
        "duruşu",
        "kalitesi",
        "göründüğü",
        "sardı",
        "bedeninizden",
        "alin",
        "bayıldım",
        "almalısınız"
      ],
      "positive_pct": 83.3,
      "negative_pct": 0.0,
      "neutral_pct": 16.7,
      "sample_reviews": [
        "beklediğimden de güzel geldi içiniz rahat kendi bedeninizi alabilirsiniz",
        "tahminimden güzel teşekkürler iç göstermiyor herkes kendi bedenini alsın",
        "kendi bedeninizi alabilirsiniz 170 boy 65 kg m beden tam oldu güzel ürün"
      ],
      "all_reviews": [
        {
          "text": "beklediğimden de güzel geldi içiniz rahat kendi bedeninizi alabilirsiniz",
          "score": 5.0
        },
        {
          "text": "tam bedeninizi alın çok iyi durdu",
          "score": 5.0
        },
        {
          "text": "tam bedeninizi alabilirsiniz ben çok beğendim",
          "score": 5.0
        },
        {
          "text": "tahminimden güzel teşekkürler iç göstermiyor herkes kendi bedenini alsın",
          "score": 5.0
        },
        {
          "text": "kendi bedeninizi alabilirsiniz 170 boy 65 kg m beden tam oldu güzel ürün",
          "score": 4.0
        }
      ],
      "icon": "💬"
    },
    {
      "name": "Kaliteli Rahat",
      "review_count": 7,
      "avg_score": 5.0,
      "sentiment": "positive",
      "sentiment_label": "Olumlu",
      "top_terms": [
        "kaliteli rahat",
        "toparlayıcı",
        "oturuyor",
        "bedeni",
        "alınmalı",
        "rahat kaliteli",
        "yumuşak",
        "kalitesi"
      ],
      "positive_pct": 100.0,
      "negative_pct": 0.0,
      "neutral_pct": 0.0,
      "sample_reviews": [
        "çok güzel kızlar ben bedenimden bir beden büyük tercih ettim ve memnun kaldım",
        "ayyy harika bi ürün çok beğendim çok güzel tam göründüğü gibi s beden aldım tam oldu 50 kiloya",
        "harika birsey çok beğendim 1 beden küçük alınabilir"
      ],
      "all_reviews": [
        {
          "text": "harika birsey çok beğendim 1 beden küçük alınabilir",
          "score": 5.0
        },
        {
          "text": "çok güzel kızlar ben bedenimden bir beden büyük tercih ettim ve memnun kaldım",
          "score": 5.0
        },
        {
          "text": "ayyy harika bi ürün çok beğendim çok güzel tam göründüğü gibi s beden aldım tam oldu 50 kiloya",
          "score": 5.0
        }
      ],
      "icon": "💬"
    },
    {
      "name": "Kumaşı & Farklı Renkleri",
      "review_count": 5,
      "avg_score": 5.0,
      "sentiment": "positive",
      "sentiment_label": "Olumlu",
      "top_terms": [
        "kumaşı",
        "oldum",
        "bedeni",
        "rengi",
        "alin",
        "sarıyor",
        "farklı renkleri",
        "yaptım"
      ],
      "positive_pct": 100.0,
      "negative_pct": 0.0,
      "neutral_pct": 0.0,
      "sample_reviews": [
        "kumaşı aşırı güzel yumuşacık asla iç belli etmiyor beli falan da çok rahat çok teşekkür ederim",
        "o kadar güzel ki tam beden alın çok rahat çok kaliteli iç göstermiyor parlaklığı da çok ayarında"
      ],
      "all_reviews": [
        {
          "text": "kumaşı aşırı güzel yumuşacık asla iç belli etmiyor beli falan da çok rahat çok teşekkür ederim",
          "score": 5.0
        },
        {
          "text": "o kadar güzel ki tam beden alın çok rahat çok kaliteli iç göstermiyor parlaklığı da çok ayarında",
          "score": 5.0
        }
      ],
      "icon": "💬"
    },
    {
      "name": "Fiyat Performans",
      "review_count": 3,
      "avg_score": 5.0,
      "sentiment": "positive",
      "sentiment_label": "Olumlu",
      "top_terms": [
        "fiyata",
        "fiyat",
        "efsane",
        "paketleme",
        "aldığım",
        "edebilirsiniz",
        "diyebilirim",
        "fiyat performans"
      ],
      "positive_pct": 100.0,
      "negative_pct": 0.0,
      "neutral_pct": 0.0,
      "sample_reviews": [
        "beklediğimden güzel cıktı tam beden alabilirsiniz güzel topluyor fiyat olarak da cok uygun"
      ],
      "all_reviews": [
        {
          "text": "beklediğimden güzel cıktı tam beden alabilirsiniz güzel topluyor fiyat olarak da cok uygun",
          "score": 5.0
        }
      ],
      "icon": "💬"
    },
    {
      "name": "Kumaşı",
      "review_count": 3,
      "avg_score": 5.0,
      "sentiment": "positive",
      "sentiment_label": "Olumlu",
      "top_terms": [
        "kumaşı",
        "diye",
        "kumaş",
        "kalıbı",
        "iade",
        "esnek",
        "bayıldım",
        "baya"
      ],
      "positive_pct": 100.0,
      "negative_pct": 0.0,
      "neutral_pct": 0.0,
      "sample_reviews": [
        "kumaşı çok rahat 65 kilo l beden aldım beklentimin üstünde geldi bayıldım"
      ],
      "all_reviews": [
        {
          "text": "kumaşı çok rahat 65 kilo l beden aldım beklentimin üstünde geldi bayıldım",
          "score": 5.0
        }
      ],
      "icon": "💬"
    },
    {
      "name": "Rahat Kullanışlı",
      "review_count": 3,
      "avg_score": 5.0,
      "sentiment": "positive",
      "sentiment_label": "Olumlu",
      "top_terms": [
        "ürünler",
        "teslimat",
        "kullanışlı",
        "özellikle",
        "rahat kullanışlı",
        "oldum",
        "aldık",
        "göründüğü"
      ],
      "positive_pct": 100.0,
      "negative_pct": 0.0,
      "neutral_pct": 0.0,
      "sample_reviews": [
        "48 kiloyum xs aldım gayet güzel oldu herkeze tavsiye ediyorum teşekkür ederiz"
      ],
      "all_reviews": [
        {
          "text": "48 kiloyum xs aldım gayet güzel oldu herkeze tavsiye ediyorum teşekkür ederiz",
          "score": 5.0
        }
      ],
      "icon": "💬"
    },
    {
      "name": "Sıcacık",
      "review_count": 2,
      "avg_score": 5.0,
      "sentiment": "positive",
      "sentiment_label": "Olumlu",
      "top_terms": [
        "kaliteli kaliteli",
        "rahat rahat",
        "sıcacık tutuyor",
        "sıcacık",
        "bedenınızı",
        "derim",
        "tutuyor",
        "yumuşacık"
      ],
      "positive_pct": 100.0,
      "negative_pct": 0.0,
      "neutral_pct": 0.0,
      "sample_reviews": [
        "oldukça rahat ve ince olmasina rağmen ısıtıyor tam bedeninizi alin"
      ],
      "all_reviews": [
        {
          "text": "oldukça rahat ve ince olmasina rağmen ısıtıyor tam bedeninizi alin",
          "score": 5.0
        }
      ],
      "icon": "💬"
    },
    {
      "name": "Renkleri & Kaliteli Ürünler",
      "review_count": 2,
      "avg_score": 5.0,
      "sentiment": "positive",
      "sentiment_label": "Olumlu",
      "top_terms": [
        "renkleri",
        "kaliteli ürünler",
        "notunuz",
        "paketleme özenliydi",
        "özenliydi",
        "rahat kullanışlı",
        "paketleme",
        "kalite"
      ],
      "positive_pct": 100.0,
      "negative_pct": 0.0,
      "neutral_pct": 0.0,
      "sample_reviews": [
        "bedeni olsa yeşilini de alacaktım her rengini aldım"
      ],
      "all_reviews": [
        {
          "text": "bedeni olsa yeşilini de alacaktım her rengini aldım",
          "score": 5.0
        }
      ],
      "icon": "💬"
    }
  ],
  "top_reviews": [
    "tayt çok güzel 75 kg 1.68 boy m aldım tam oldu kalçam geniş olmasına rağmen tam sardı yüksek bel oluşu da çok güzel",
    "tayt çok güzel 75 kg 1.68 boy m aldım tam oldu kalçam geniş olmasına rağmen tam sardı yüksek bel oluşu da çok güzel",
    "tayt çok güzel 75 kg 1.68 boy m aldım tam oldu kalçam geniş olmasına rağmen tam sardı yüksek bel oluşu da çok güzel",
    "o kadar güzel ki tam beden alın çok rahat çok kaliteli iç göstermiyor parlaklığı da çok ayarında",
    "o kadar güzel ki tam beden alın çok rahat çok kaliteli iç göstermiyor parlaklığı da çok ayarında"
  ],
  "generated_at": "2026-04-06"
}