{
  "product_id": "d5955b2edc93",
  "product_name": "Lantliv 4 Adet Diz Altı Pamuklu Penye Tayt, %95 Pamuklu %5 Likralı Tayt, Kapri Tayt, İçlik, Büyük Beden Tayt - Fiyatı, Yorumları",
  "product_url": "https://www.trendyol.com/lantliv/4-adet-diz-alti-pamuklu-penye-tayt-95-pamuklu-5-likrali-tayt-kapri-tayt-iclik-buyuk-beden-tayt-p-982836490",
  "category": "kadin_tayt",
  "category_label": "Kadın Tayt",
  "total_reviews": 40,
  "overall_score": 4.75,
  "overall_sentiment": "positive",
  "stars": "★★★★½",
  "summary": "**Lantliv 4 Adet Diz Altı Pamuklu Penye Tayt, %95 Pamuklu** için 40 müşteri yorumu incelenmiştir. Ürün, kullanıcılar tarafından son derece olumlu karşılanmakta ve yüksek puan almaktadır.\n• **Kaliteli Rahat** konusundaki görüşler dengeli bir seyir izlemekte; hem olumlu hem olumsuz değerlendirmeler yer almaktadır; **toparlayıcı** ve **bedeni** konusu özellikle vurgulanmaktadır. Örnek kullanıcı ifadesi: \"Çok güzeller tam beden alın biraz ince sadece ben rahat olsun diye 1 beden büyük aldı…\"\n• **Kumaşı**, müşteriler tarafından özellikle takdir gören bir özellik olarak öne çıkmaktadır, **kumaş** ve **kalıbı** başta olmak üzere. Örnek kullanıcı ifadesi: \"Ilk defa bu kadar kaliteli bir tayt bulabildim hem kalıbı rahat hemde kumaşı inanılma…\"\n• Kullanıcılar **Kumaşı & Farklı Renkleri** hakkında genel itibarıyla memnuniyetlerini dile getirmektedir; **bedeni** ve **rengi** konusu özellikle vurgulanmaktadır. Örnek kullanıcı ifadesi: \"Kumaş kalitesine bayıldım tam kalıp herkese tavsiye ederim\"\n• **Fiyata & Kaliteli Ürünler** açısından değerlendirmeler son derece olumlu bir tablo ortaya koymaktadır, **fiyat** ve **uygun** başta olmak üzere. Örnek kullanıcı ifadesi: \"Paketleme çok özenli teslimat hızlıydı iyi ki 3xl sipariş ettim tam oldu çok beğendim…\"\n• Müşteri yorumlarında **Kalıp Rahat** başlığı altında yoğun bir memnuniyet gözlemlenmektedir; **esnek** konusu özellikle vurgulanmaktadır. Örnek kullanıcı ifadesi: \"Annem için aldım gayet memnun kaldı\"",
  "score_distribution": {
    "1": 2,
    "2": 0,
    "3": 0,
    "4": 2,
    "5": 36
  },
  "aspects": [
    {
      "name": "Kaliteli Rahat",
      "review_count": 10,
      "avg_score": 4.2,
      "sentiment": "neutral",
      "sentiment_label": "Genel Olumlu",
      "top_terms": [
        "kaliteli rahat",
        "toparlayıcı",
        "oturuyor",
        "bedeni",
        "alınmalı",
        "rahat kaliteli",
        "yumuşak",
        "kalitesi"
      ],
      "positive_pct": 80.0,
      "negative_pct": 20.0,
      "neutral_pct": 0.0,
      "sample_reviews": [
        "tam bedenime oldu oldukça da kaliteli tam bir fp ürünü tekrardan almayı düşünüyorum",
        "yumuşak penye ve belde bir tayt çok rahat",
        "çok güzeller tam beden alın biraz ince sadece ben rahat olsun diye 1 beden büyük aldım"
      ],
      "all_reviews": [
        {
          "text": "çok güzeller tam beden alın biraz ince sadece ben rahat olsun diye 1 beden büyük aldım",
          "score": 5.0
        },
        {
          "text": "yumuşak penye ve belde bir tayt çok rahat",
          "score": 5.0
        },
        {
          "text": "annem için aldım çok beğendi",
          "score": 5.0
        },
        {
          "text": "tam bedenime oldu oldukça da kaliteli tam bir fp ürünü tekrardan almayı düşünüyorum",
          "score": 5.0
        },
        {
          "text": "ben l beden sipariş verdim xl yollamışsınız geri iade ediyorum",
          "score": 1.0
        }
      ],
      "icon": "💬"
    },
    {
      "name": "Kumaşı",
      "review_count": 8,
      "avg_score": 5.0,
      "sentiment": "positive",
      "sentiment_label": "Olumlu",
      "top_terms": [
        "kumaşı",
        "diye",
        "kumaş",
        "kalıbı",
        "iade",
        "esnek",
        "bayıldım",
        "baya"
      ],
      "positive_pct": 100.0,
      "negative_pct": 0.0,
      "neutral_pct": 0.0,
      "sample_reviews": [
        "ilk defa bu kadar kaliteli bir tayt bulabildim hem kalıbı rahat hemde kumaşı inanılmaz güzel",
        "2.5 aydir giyiyorum çok çok güzel kilolu olduğum için taytlari bu kadar uzun süre giyemez idim ama bacak arasında dellinme vs yok kumaşı çok güzel rahatlığı efsane kesinlikle tavsiye ederim",
        "yaz için çok güzeller bir beden büyük alın kalıbı küçük ben m almıştım ama bana l göndermişlerdi ama iyi ki göndermişler tam oldu ben memnun kaldım"
      ],
      "all_reviews": [
        {
          "text": "yaz için çok güzeller bir beden büyük alın kalıbı küçük ben m almıştım ama bana l göndermişlerdi ama iyi ki göndermişler tam oldu ben memnun kaldım",
          "score": 5.0
        },
        {
          "text": "ilk defa bu kadar kaliteli bir tayt bulabildim hem kalıbı rahat hemde kumaşı inanılmaz güzel",
          "score": 5.0
        },
        {
          "text": "penye yumuşacık çok beğendim yıkadım çekmede yapmadı",
          "score": 5.0
        },
        {
          "text": "2.5 aydir giyiyorum çok çok güzel kilolu olduğum için taytlari bu kadar uzun süre giyemez idim ama bacak arasında dellinme vs yok kumaşı çok güzel rahatlığı efsane kesinlikle tavsiye ederim",
          "score": 5.0
        }
      ],
      "icon": "💬"
    },
    {
      "name": "Kumaşı & Farklı Renkleri",
      "review_count": 6,
      "avg_score": 5.0,
      "sentiment": "positive",
      "sentiment_label": "Olumlu",
      "top_terms": [
        "kumaşı",
        "oldum",
        "bedeni",
        "rengi",
        "alin",
        "sarıyor",
        "farklı renkleri",
        "yaptım"
      ],
      "positive_pct": 100.0,
      "negative_pct": 0.0,
      "neutral_pct": 0.0,
      "sample_reviews": [
        "çok rahat kalitesi kumaşı çok iyi",
        "kumaş kalitesine bayıldım tam kalıp herkese tavsiye ederim",
        "kumaşları çok iyi kullanışlı ve uygun fiyatlı"
      ],
      "all_reviews": [
        {
          "text": "kumaş kalitesine bayıldım tam kalıp herkese tavsiye ederim",
          "score": 5.0
        },
        {
          "text": "çok rahat kalitesi kumaşı çok iyi",
          "score": 5.0
        },
        {
          "text": "kumaşları çok iyi kullanışlı ve uygun fiyatlı",
          "score": 5.0
        }
      ],
      "icon": "💬"
    },
    {
      "name": "Fiyata & Kaliteli Ürünler",
      "review_count": 6,
      "avg_score": 4.67,
      "sentiment": "positive",
      "sentiment_label": "Olumlu",
      "top_terms": [
        "fiyata",
        "beklemiyordum",
        "fiyat",
        "uygun",
        "aldık",
        "rengi",
        "biri",
        "baya"
      ],
      "positive_pct": 66.7,
      "negative_pct": 0.0,
      "neutral_pct": 33.3,
      "sample_reviews": [
        "paketleme çok özenli teslimat hızlıydı iyi ki 3xl sipariş ettim tam oldu çok beğendim tekrar sipariş oluşturacağım inşaallah",
        "bir tık beden kısımları bol ama olsun güzel ve kargo hızlıydı",
        "kargo çok bekletti ama kaliteli ürünler bele kadar sarıyor"
      ],
      "all_reviews": [
        {
          "text": "bir tık beden kısımları bol ama olsun güzel ve kargo hızlıydı",
          "score": 5.0
        },
        {
          "text": "paketleme çok özenli teslimat hızlıydı iyi ki 3xl sipariş ettim tam oldu çok beğendim tekrar sipariş oluşturacağım inşaallah",
          "score": 5.0
        },
        {
          "text": "kargo çok bekletti ama kaliteli ürünler bele kadar sarıyor",
          "score": 4.0
        }
      ],
      "icon": "💬"
    },
    {
      "name": "Kalıp Rahat",
      "review_count": 2,
      "avg_score": 5.0,
      "sentiment": "positive",
      "sentiment_label": "Olumlu",
      "top_terms": [
        "toparlıyor",
        "kalıp",
        "beyendim",
        "severek",
        "baya",
        "esnek",
        "kalıp rahat",
        "bayıldım"
      ],
      "positive_pct": 100.0,
      "negative_pct": 0.0,
      "neutral_pct": 0.0,
      "sample_reviews": [
        "annem için aldım gayet memnun kaldı"
      ],
      "all_reviews": [
        {
          "text": "annem için aldım gayet memnun kaldı",
          "score": 5.0
        }
      ],
      "icon": "💬"
    },
    {
      "name": "Duruşu & Kalitesi",
      "review_count": 2,
      "avg_score": 5.0,
      "sentiment": "positive",
      "sentiment_label": "Olumlu",
      "top_terms": [
        "duruşu",
        "kalitesi",
        "göründüğü",
        "sardı",
        "bedeninizden",
        "alin",
        "bayıldım",
        "almalısınız"
      ],
      "positive_pct": 100.0,
      "negative_pct": 0.0,
      "neutral_pct": 0.0,
      "sample_reviews": [
        "etek için bir tık fazla uzun dokusu falan harika kesinlikle alın"
      ],
      "all_reviews": [
        {
          "text": "etek için bir tık fazla uzun dokusu falan harika kesinlikle alın",
          "score": 5.0
        }
      ],
      "icon": "💬"
    },
    {
      "name": "Fiyat Performans",
      "review_count": 2,
      "avg_score": 5.0,
      "sentiment": "positive",
      "sentiment_label": "Olumlu",
      "top_terms": [
        "fiyata",
        "fiyat",
        "efsane",
        "paketleme",
        "aldığım",
        "edebilirsiniz",
        "diyebilirim",
        "fiyat performans"
      ],
      "positive_pct": 100.0,
      "negative_pct": 0.0,
      "neutral_pct": 0.0,
      "sample_reviews": [
        "güvenerek satın alabilirsiniz tabi satıcı çok önemli"
      ],
      "all_reviews": [
        {
          "text": "güvenerek satın alabilirsiniz tabi satıcı çok önemli",
          "score": 5.0
        }
      ],
      "icon": "💬"
    },
    {
      "name": "Sıcacık",
      "review_count": 2,
      "avg_score": 5.0,
      "sentiment": "positive",
      "sentiment_label": "Olumlu",
      "top_terms": [
        "kaliteli kaliteli",
        "rahat rahat",
        "sıcacık tutuyor",
        "sıcacık",
        "bedenınızı",
        "derim",
        "tutuyor",
        "yumuşacık"
      ],
      "positive_pct": 100.0,
      "negative_pct": 0.0,
      "neutral_pct": 0.0,
      "sample_reviews": [
        "çok kaliteli"
      ],
      "all_reviews": [
        {
          "text": "çok kaliteli",
          "score": 5.0
        }
      ],
      "icon": "💬"
    },
    {
      "name": "Rahat Kullanışlı",
      "review_count": 2,
      "avg_score": 5.0,
      "sentiment": "positive",
      "sentiment_label": "Olumlu",
      "top_terms": [
        "ürünler",
        "teslimat",
        "kullanışlı",
        "özellikle",
        "rahat kullanışlı",
        "oldum",
        "aldık",
        "göründüğü"
      ],
      "positive_pct": 100.0,
      "negative_pct": 0.0,
      "neutral_pct": 0.0,
      "sample_reviews": [
        "hemen geldi teşekkür ederim gayet güzel kaliteli"
      ],
      "all_reviews": [
        {
          "text": "hemen geldi teşekkür ederim gayet güzel kaliteli",
          "score": 5.0
        }
      ],
      "icon": "💬"
    }
  ],
  "top_reviews": [
    "2.5 aydir giyiyorum çok çok güzel kilolu olduğum için taytlari bu kadar uzun süre giyemez idim ama bacak arasında dellinme vs yok kumaşı çok güzel rahatlığı efsane kesinlikle tavsiye ederim",
    "2.5 aydir giyiyorum çok çok güzel kilolu olduğum için taytlari bu kadar uzun süre giyemez idim ama bacak arasında dellinme vs yok kumaşı çok güzel rahatlığı efsane kesinlikle tavsiye ederim",
    "yaz için çok güzeller bir beden büyük alın kalıbı küçük ben m almıştım ama bana l göndermişlerdi ama iyi ki göndermişler tam oldu ben memnun kaldım",
    "yaz için çok güzeller bir beden büyük alın kalıbı küçük ben m almıştım ama bana l göndermişlerdi ama iyi ki göndermişler tam oldu ben memnun kaldım",
    "paketleme çok özenli teslimat hızlıydı iyi ki 3xl sipariş ettim tam oldu çok beğendim tekrar sipariş oluşturacağım inşaallah"
  ],
  "generated_at": "2026-04-06"
}